crowdin_api/__init__.py
crowdin_api/client.py
crowdin_api/enums.py
crowdin_api/exceptions.py
crowdin_api/fixtures.py
crowdin_api/parser.py
crowdin_api/requester.py
crowdin_api/sorting.py
crowdin_api/status.py
crowdin_api/typing.py
crowdin_api/utils.py
crowdin_api/api_resources/__init__.py
crowdin_api/api_resources/enums.py
crowdin_api/api_resources/abstract/__init__.py
crowdin_api/api_resources/abstract/resources.py
crowdin_api/api_resources/ai/__init__.py
crowdin_api/api_resources/ai/enums.py
crowdin_api/api_resources/ai/resource.py
crowdin_api/api_resources/ai/types.py
crowdin_api/api_resources/application/__init__.py
crowdin_api/api_resources/application/enums.py
crowdin_api/api_resources/application/resource.py
crowdin_api/api_resources/application/types.py
crowdin_api/api_resources/branches/__init__.py
crowdin_api/api_resources/branches/enums.py
crowdin_api/api_resources/branches/resource.py
crowdin_api/api_resources/branches/types.py
crowdin_api/api_resources/bundles/__init__.py
crowdin_api/api_resources/bundles/enums.py
crowdin_api/api_resources/bundles/resource.py
crowdin_api/api_resources/bundles/types.py
crowdin_api/api_resources/clients/__init__.py
crowdin_api/api_resources/clients/resource.py
crowdin_api/api_resources/dictionaries/__init__.py
crowdin_api/api_resources/dictionaries/resource.py
crowdin_api/api_resources/dictionaries/types.py
crowdin_api/api_resources/distributions/__init__.py
crowdin_api/api_resources/distributions/enums.py
crowdin_api/api_resources/distributions/resource.py
crowdin_api/api_resources/distributions/types.py
crowdin_api/api_resources/fields/__init__.py
crowdin_api/api_resources/fields/enums.py
crowdin_api/api_resources/fields/resource.py
crowdin_api/api_resources/fields/types.py
crowdin_api/api_resources/glossaries/__init__.py
crowdin_api/api_resources/glossaries/enums.py
crowdin_api/api_resources/glossaries/resource.py
crowdin_api/api_resources/glossaries/types.py
crowdin_api/api_resources/groups/__init__.py
crowdin_api_client-1.25.0.dist-info/LICENSE
crowdin_api_client-1.25.0.dist-info/METADATA
crowdin_api_client-1.25.0.dist-info/WHEEL
crowdin_api_client-1.25.0.dist-info/top_level.txt
crowdin_api_client-1.25.0.dist-info/RECORD
