Metadata-Version: 2.1
Name: crowdin-api-client
Version: 1.25.0
Summary: Python client library for Crowdin API v2
Home-page: https://github.com/crowdin/crowdin-api-client-python
Author: Сrowdin
Author-email: support@crowdin.com
License: MIT
Project-URL: Documentation, https://support.crowdin.com/api/v2/
Project-URL: Source Code, https://github.com/crowdin/crowdin-api-client-python
Classifier: Programming Language :: Python
Classifier: Programming Language :: Python :: 3
Classifier: Programming Language :: Python :: 3.8
Classifier: Programming Language :: Python :: 3.9
Classifier: Programming Language :: Python :: 3.10
Classifier: Programming Language :: Python :: 3.11
Classifier: Programming Language :: Python :: 3.12
Requires-Python: >=3.8
License-File: LICENSE
Requires-Dist: requests >=2.31.0
Requires-Dist: deprecated
Requires-Dist: typing-extensions ; python_version < "3.8.0"
